etag_generator/__init__.py
etag_generator-0.9.1.dist-info/METADATA
etag_generator-0.9.1.dist-info/WHEEL
etag_generator-0.9.1.dist-info/licenses/LICENSE
etag_generator-0.9.1.dist-info/RECORD
