Metadata-Version: 2.4
Name: etag_generator
Version: 0.9.1
Summary: Given a JSON object (python dict), generate a stable value suitable as an ETag
Project-URL: Homepage, https://github.com/paulprogrammer/py-json-etag-generator
Project-URL: Issues, https://github.com/paulprogrammer/py-json-etag-generator/issues
Author-email: Paul Williams <paul_williams@epam.com>
License-Expression: Apache-2.0
License-File: LICENSE
Keywords: etag,json
Classifier: Development Status :: 4 - Beta
Classifier: Environment :: Web Environment
Classifier: Intended Audience :: Developers
Classifier: License :: OSI Approved :: Apache Software License
Classifier: Natural Language :: English
Classifier: Operating System :: OS Independent
Classifier: Programming Language :: Python :: 3 :: Only
Classifier: Topic :: Internet :: WWW/HTTP
Classifier: Topic :: Utilities
Requires-Python: >=3.8
Requires-Dist: colorlog==6.9.0
Requires-Dist: iniconfig==2.0.0
Requires-Dist: pluggy==1.5.0
Requires-Dist: pytest==8.3.5
